ofilepy
